letmeknowclient/__init__.py
letmeknowclient/const.py
letmeknowclient/exceptions.py
letmeknowclient/lmk.py
letmeknowclient/models.py
letmeknowclient/py.typed
letmeknowclient/utils.py
letmeknowclient-1.0.0.dist-info/LICENSE
letmeknowclient-1.0.0.dist-info/METADATA
letmeknowclient-1.0.0.dist-info/WHEEL
letmeknowclient-1.0.0.dist-info/RECORD
